setup.py
webserver_extentions/__init__.py
webserver_extentions/run.py
webserver_extentions.egg-info/PKG-INFO
webserver_extentions.egg-info/SOURCES.txt
webserver_extentions.egg-info/dependency_links.txt
webserver_extentions.egg-info/requires.txt
webserver_extentions.egg-info/top_level.txt
webserver_extentions/common/__init__.py
webserver_extentions/common/get_params_from_config.py
webserver_extentions/common/log.py
webserver_extentions/extention/__init__.py
webserver_extentions/extention/blueprint_app.py
webserver_extentions/extention/celeryTask.py
webserver_extentions/extention/db.py