Metadata-Version: 1.0
Name: webserver-extentions
Version: 19.6.14
Summary: flask and webpy frame
Home-page: https://github.com/lijiacaigit/webserver_extentions
Author: Lijiacai
Author-email: 1050518702@qq.com
License: UNKNOWN
Keywords: pip,webserver,extentions,
Platform: any
